{
    "title": "Verify Roblox Account via In-Game!",
    "icon_url": "https://cdn.efaz.dev/cdn/png/logo.png",
    "questions": [
        {
            "name": "Roblox Username",
            "jsonName": "Roblox-Username",
            "type": "Short Response",
            "placeholder": "Enter your roblox username!",
            "required": true,
            "custom_class": ""
        }
    ],
    "googleCaptcha": {
        "enabled": false,
        "siteKey": "",
        "jsonName": "g_captcha"
    },
    "cloudflareCaptcha": {
        "enabled": true,
        "siteKey": "0x4AAAAAAAKmqoGdEw41aH3A",
        "jsonName": "c_captcha"
    },
    "hideModeSelection": true,
    "showCurrentMode": true,
    "defaultMode": "Verification",
    "modes": [
        {
            "name": "Verification",
            "api_url": "https://dashboard.efaz.dev/api/auth/change-password",
            "type_of_api": "PATCH",
            "formatted": [
                {
                    "questionName": "Roblox Username",
                    "jsonName": "Roblox-Username",
                    "in": "Body"
                }
            ],
            "thanksMessage": "This Roblox Account has been requested to be verified successfully! Join this game to connect the accounts: https://www.roblox.com/games/14986642611/Efazs-Verification-Center",
            "showTryAgainOnSuccess": false,
            "showTypeOfModeInBody": false
        }
    ],
    "specific_settings": {
        "showRequiredText": true,
        "custom_css": "https://cdn.efaz.dev/cdn/other/htmlUI.css",
        "include_cookies": true
    }
}